{
  "attributes": [
    {
      "allow_nil?": false,
      "default": "fragment(\"gen_random_uuid()\")",
      "generated?": false,
      "precision": null,
      "primary_key?": true,
      "references": null,
      "scale": null,
      "size": null,
      "source": "id",
      "type": "uuid"
    },
    {
      "allow_nil?": false,
      "default": "nil",
      "generated?": false,
      "precision": null,
      "primary_key?": false,
      "references": null,
      "scale": null,
      "size": null,
      "source": "username",
      "type": "citext"
    },
    {
      "allow_nil?": false,
      "default": "nil",
      "generated?": false,
      "precision": null,
      "primary_key?": false,
      "references": null,
      "scale": null,
      "size": null,
      "source": "email",
      "type": "citext"
    },
    {
      "allow_nil?": false,
      "default": "nil",
      "generated?": false,
      "precision": null,
      "primary_key?": false,
      "references": null,
      "scale": null,
      "size": null,
      "source": "password_hash",
      "type": "text"
    },
    {
      "allow_nil?": false,
      "default": "\"active\"",
      "generated?": false,
      "precision": null,
      "primary_key?": false,
      "references": null,
      "scale": null,
      "size": null,
      "source": "status",
      "type": "text"
    },
    {
      "allow_nil?": false,
      "default": "nil",
      "generated?": false,
      "precision": null,
      "primary_key?": false,
      "references": null,
      "scale": null,
      "size": null,
      "source": "birthday",
      "type": "date"
    },
    {
      "allow_nil?": true,
      "default": "nil",
      "generated?": false,
      "precision": null,
      "primary_key?": false,
      "references": null,
      "scale": null,
      "size": null,
      "source": "promo_code",
      "type": "text"
    },
    {
      "allow_nil?": false,
      "default": "nil",
      "generated?": false,
      "precision": null,
      "primary_key?": false,
      "references": null,
      "scale": null,
      "size": null,
      "source": "tos_agreed_at",
      "type": "utc_datetime"
    },
    {
      "allow_nil?": false,
      "default": "nil",
      "generated?": false,
      "precision": null,
      "primary_key?": false,
      "references": null,
      "scale": null,
      "size": null,
      "source": "tos_version",
      "type": "text"
    },
    {
      "allow_nil?": false,
      "default": "fragment(\"(now() AT TIME ZONE 'utc')\")",
      "generated?": false,
      "precision": null,
      "primary_key?": false,
      "references": null,
      "scale": null,
      "size": null,
      "source": "inserted_at",
      "type": "utc_datetime_usec"
    },
    {
      "allow_nil?": false,
      "default": "fragment(\"(now() AT TIME ZONE 'utc')\")",
      "generated?": false,
      "precision": null,
      "primary_key?": false,
      "references": null,
      "scale": null,
      "size": null,
      "source": "updated_at",
      "type": "utc_datetime_usec"
    }
  ],
  "base_filter": null,
  "check_constraints": [],
  "create_table_options": null,
  "custom_indexes": [],
  "custom_statements": [],
  "has_create_action": true,
  "hash": "DA1F3DF9CE0EE0EB5C690AA3114D70CF982FB12AF88FB8924A155471D34FC817",
  "identities": [
    {
      "all_tenants?": false,
      "base_filter": null,
      "index_name": "users_unique_email_index",
      "keys": [
        {
          "type": "atom",
          "value": "email"
        }
      ],
      "name": "unique_email",
      "nils_distinct?": true,
      "where": null
    },
    {
      "all_tenants?": false,
      "base_filter": null,
      "index_name": "users_unique_username_index",
      "keys": [
        {
          "type": "atom",
          "value": "username"
        }
      ],
      "name": "unique_username",
      "nils_distinct?": true,
      "where": null
    }
  ],
  "multitenancy": {
    "attribute": null,
    "global": null,
    "strategy": null
  },
  "repo": "Elixir.Auth.Repo",
  "schema": null,
  "table": "users"
}